registry_utils/Register.py
registry_utils/__init__.py
mca_company_registry_utils-1.1.0.dist-info/METADATA
mca_company_registry_utils-1.1.0.dist-info/WHEEL
mca_company_registry_utils-1.1.0.dist-info/top_level.txt
mca_company_registry_utils-1.1.0.dist-info/RECORD
